optaplus/__init__.py
optaplus-0.1.dist-info/METADATA
optaplus-0.1.dist-info/RECORD
optaplus-0.1.dist-info/WHEEL
optaplus-0.1.dist-info/top_level.txt
